aidops_utility/__init__.py
aidops_utility/serialization.py
aidops_utility-1.1.20220301.1.dist-info/LICENSE
aidops_utility-1.1.20220301.1.dist-info/METADATA
aidops_utility-1.1.20220301.1.dist-info/WHEEL
aidops_utility-1.1.20220301.1.dist-info/top_level.txt
aidops_utility-1.1.20220301.1.dist-info/RECORD
