Metadata-Version: 2.1
Name: aidops-utility
Version: 1.1.20220301.1
Summary: AidOps base utilities
Home-page: https://github.com/pypa/sampleproject
Author: ac4y
Author-email: appcloud4you@gmail.com
License: UNKNOWN
Project-URL: Bug Tracker, https://github.com/pypa/sampleproject/issues
Platform: UNKNOWN
Classifier: Programming Language :: Python :: 3
Classifier: License :: OSI Approved :: MIT License
Classifier: Operating System :: OS Independent
Requires-Python: >=3.6
License-File: LICENSE
